valenoq/__init__.py
valenoq/api/__init__.py
valenoq/api/config.py
valenoq/api/get.py
valenoq/api/request.py
valenoq/api/status.py
valenoq-0.0.4.dist-info/METADATA
valenoq-0.0.4.dist-info/WHEEL
valenoq-0.0.4.dist-info/top_level.txt
valenoq-0.0.4.dist-info/RECORD
