Metadata-Version: 2.1
Name: valenoq
Version: 0.0.4
Summary: Python package to interact with valenoq.com RESTful API
Home-page: http://github.com/samarkanov/valenoq
Author: valenoq.com
Author-email: samarkanov@gmail.com
License: MIT
Platform: UNKNOWN
Requires-Python: >=3.5
Requires-Dist: numpy (>=1.8)
Requires-Dist: pandas (>=0.14)
Requires-Dist: requests (>=2.7.0)
